lcp_chart_mcp/__init__.py
lcp_chart_mcp/server.py
lcp_chart_mcp-0.1.1.dist-info/METADATA
lcp_chart_mcp-0.1.1.dist-info/WHEEL
lcp_chart_mcp-0.1.1.dist-info/entry_points.txt
lcp_chart_mcp-0.1.1.dist-info/RECORD
