Metadata-Version: 2.4
Name: lcp-chart-mcp
Version: 0.1.1
Summary: 一個 MCP 伺服器，提供圖表生成工具
Requires-Dist: httpx
Requires-Dist: mcp
